odoo8_addon_website_sale_survey-8.0.1.0.0-py2.7-nspkg.pth
odoo8_addon_website_sale_survey-8.0.1.0.0.dist-info/top_level.txt
odoo8_addon_website_sale_survey-8.0.1.0.0.dist-info/WHEEL
odoo8_addon_website_sale_survey-8.0.1.0.0.dist-info/RECORD
odoo8_addon_website_sale_survey-8.0.1.0.0.dist-info/metadata.json
odoo8_addon_website_sale_survey-8.0.1.0.0.dist-info/DESCRIPTION.rst
odoo8_addon_website_sale_survey-8.0.1.0.0.dist-info/METADATA
odoo8_addon_website_sale_survey-8.0.1.0.0.dist-info/namespace_packages.txt
odoo_addons/website_sale_survey/__openerp__.py
odoo_addons/website_sale_survey/__init__.py
odoo_addons/website_sale_survey/README.rst
odoo_addons/website_sale_survey/models/sale.py
odoo_addons/website_sale_survey/models/__init__.py
odoo_addons/website_sale_survey/models/survey.py
odoo_addons/website_sale_survey/i18n/es.po
odoo_addons/website_sale_survey/views/survey_view.xml
odoo_addons/website_sale_survey/views/template.xml
odoo_addons/website_sale_survey/controllers/main.py
odoo_addons/website_sale_survey/controllers/__init__.py
odoo_addons/website_sale_survey/tests/test_website_sale_survey.py
odoo_addons/website_sale_survey/tests/__init__.py
